client.py
mseep_s3_mcp_server-0.1.3.dist-info/licenses/LICENSE
s3_mcp_server/__init__.py
s3_mcp_server/server.py
s3_mcp_server/resources/__init__.py
s3_mcp_server/resources/s3_resource.py
mseep_s3_mcp_server-0.1.3.dist-info/METADATA
mseep_s3_mcp_server-0.1.3.dist-info/WHEEL
mseep_s3_mcp_server-0.1.3.dist-info/entry_points.txt
mseep_s3_mcp_server-0.1.3.dist-info/top_level.txt
mseep_s3_mcp_server-0.1.3.dist-info/RECORD
