Metadata-Version: 2.4
Name: mseep-s3-mcp-server
Version: 0.1.3
Summary: A MCP server project
Author-email: mseep <support@skydeck.ai>
Requires-Python: >=3.12
License-File: LICENSE
Requires-Dist: aioboto3>=13.2.0
Requires-Dist: mcp>=1.0.0
Requires-Dist: python-dotenv>=1.0.1
Dynamic: license-file
